setup_chromedriver/__init__.py
setup_chromedriver/main.py
setup_chromedriver/setup_chromedriver.py
setup_chromedriver-0.1.1.dist-info/LICENSE
setup_chromedriver-0.1.1.dist-info/METADATA
setup_chromedriver-0.1.1.dist-info/WHEEL
setup_chromedriver-0.1.1.dist-info/top_level.txt
setup_chromedriver-0.1.1.dist-info/RECORD
