Metadata-Version: 2.2
Name: setup-chromedriver
Version: 0.1.1
Summary: A Python library to automatically manage and set up ChromeDriver.
Home-page: https://github.com/RasikhAli/setup_chromedriver
Author: Rasikh Ali
Author-email: rasikh.ali1234@gmail.com
Classifier: Programming Language :: Python :: 3
Classifier: License :: OSI Approved :: MIT License
Classifier: Operating System :: OS Independent
Requires-Python: >=3.6
License-File: LICENSE
Requires-Dist: selenium
Requires-Dist: requests
Dynamic: author
Dynamic: author-email
Dynamic: classifier
Dynamic: description
Dynamic: description-content-type
Dynamic: home-page
Dynamic: requires-dist
Dynamic: requires-python
Dynamic: summary
